CHANGELOG.md
MANIFEST.in
README.md
setup.cfg
setup.py
versioneer.py
src/libreflow/__init__.py
src/libreflow.extensions.anpo.render_jobs.egg-info/PKG-INFO
src/libreflow.extensions.anpo.render_jobs.egg-info/SOURCES.txt
src/libreflow.extensions.anpo.render_jobs.egg-info/dependency_links.txt
src/libreflow.extensions.anpo.render_jobs.egg-info/top_level.txt
src/libreflow/extensions/__init__.py
src/libreflow/extensions/anpo/__init__.py
src/libreflow/extensions/anpo/render_jobs/__init__.py
src/libreflow/extensions/anpo/render_jobs/_version.py
src/libreflow/extensions/anpo/render_jobs/ui/__init__.py
src/libreflow/extensions/anpo/render_jobs/ui/custom_widget.py